discord_status_updater/__init__.py
discord_status_updater/__main__.py
discord_status_updater/discord_client.py
discord_status_updater/discord_status_updater.py
discord_status_updater/launcher.py
discord_status_updater/plugin_base.py
discord_status_updater/plugins/__init__.py
discord_status_updater/plugins/locked.py
discord_status_updater/plugins/mpris.py
discord_status_updater-0.2.0.dist-info/LICENSE.txt
discord_status_updater-0.2.0.dist-info/METADATA
discord_status_updater-0.2.0.dist-info/WHEEL
discord_status_updater-0.2.0.dist-info/entry_points.txt
discord_status_updater-0.2.0.dist-info/top_level.txt
discord_status_updater-0.2.0.dist-info/RECORD
