Metadata-Version: 2.1
Name: discord-status-updater
Version: 0.2.0
Summary: updates Discord status depending on various conditions
Home-page: https://github.com/Kolcha/DiscordStatusUpdater
Author: Nick Korotysh
Author-email: nick.korotysh@gmail.com
License: MIT
Keywords: Discord
Classifier: Intended Audience :: End Users/Desktop
Classifier: License :: OSI Approved :: MIT License
Classifier: Operating System :: POSIX :: Linux
Classifier: Programming Language :: Python :: 3
Classifier: Topic :: Communications :: Chat
Classifier: Topic :: Utilities
Requires-Python: >=3.8
License-File: LICENSE.txt
Requires-Dist: dbus-next
Requires-Dist: python-magic
Requires-Dist: requests
